wwbot/__init__.py
wwbot/chat/__init__.py
wwbot/lib/__init__.py
wwbot/lib/logger.py
wwbot/media/__init__.py
wwbot/msg/__init__.py
wwbot/msg/file_msg.py
wwbot/msg/image_msg.py
wwbot/msg/link_msg.py
wwbot/msg/location_msg.py
wwbot/msg/markdown_msg.py
wwbot/msg/mpnews_msg.py
wwbot/msg/news_msg.py
wwbot/msg/text_msg.py
wwbot/msg/textcard_msg.py
wwbot/msg/video_msg.py
wwbot/msg/voice_msg.py
wwbot/msg/event/__init__.py
wwbot/msg/event/batch_job_result_event.py
wwbot/msg/event/click_event.py
wwbot/msg/event/enter_agent_event.py
wwbot/msg/event/location_event.py
wwbot/msg/event/location_select_event.py
wwbot/msg/event/pic_photo_or_album_event.py
wwbot/msg/event/pic_sysphoto_event.py
wwbot/msg/event/pic_weixin_event.py
wwbot/msg/event/scancode_push_event.py
wwbot/msg/event/scancode_waitmsg_event.py
wwbot/msg/event/share_agent_change_event.py
wwbot/msg/event/share_chain_change_event.py
wwbot/msg/event/subscribe_event.py
wwbot/msg/event/upload_media_job_finish_event.py
wwbot/msg/event/view_event.py
wwbot-0.0.17.dist-info/METADATA
wwbot-0.0.17.dist-info/WHEEL
wwbot-0.0.17.dist-info/top_level.txt
wwbot-0.0.17.dist-info/RECORD
