Metadata-Version: 2.4
Name: wwbot
Version: 0.0.17
Summary: A library for dealing with messages in WeWork
Home-page: https://github.com/tbbatbb/WeWorkBot
Author: tbbatbb
Author-email: 20682299+tbbatbb@users.noreply.github.com
Classifier: Development Status :: 2 - Pre-Alpha
Classifier: Framework :: Flask
Classifier: Intended Audience :: Developers
Classifier: License :: Free for non-commercial use
Classifier: Operating System :: OS Independent
Classifier: Programming Language :: Python :: 3.9
Classifier: Programming Language :: Python :: 3.10
Classifier: Programming Language :: Python :: 3.11
Classifier: Programming Language :: Python :: 3.12
Classifier: Programming Language :: Python :: 3.13
Classifier: Programming Language :: Python :: Implementation :: CPython
Classifier: Topic :: Communications :: Chat
Classifier: Topic :: Software Development :: Libraries :: Python Modules
Dynamic: author
Dynamic: author-email
Dynamic: classifier
Dynamic: description
Dynamic: description-content-type
Dynamic: home-page
Dynamic: summary
